HadithPy/HadithSearcher.py
HadithPy/__init__.py
HadithPy-1.1.1.dist-info/METADATA
HadithPy-1.1.1.dist-info/WHEEL
HadithPy-1.1.1.dist-info/top_level.txt
HadithPy-1.1.1.dist-info/RECORD
