Metadata-Version: 2.1
Name: HadithPy
Version: 1.1.1
Summary: A simple and advanced library for searching and managing Hadiths (Prophet sayings)
Author: Ahmed Negm
Author-email: a7mednegm.x@gmail.com
Classifier: Programming Language :: Python :: 3
Classifier: License :: OSI Approved :: MIT License
Classifier: Operating System :: OS Independent
Classifier: Intended Audience :: Developers
Classifier: Natural Language :: Arabic
Requires-Python: >=3.6
Requires-Dist: requests
